sideload/__init__.py
sideload/cli.py
sideload/jsonbin.py
sideload/jsonbin_connector.py
sideload/jsonbin_old.py
sideload/main.py
sideload/scripts/cleanup_pypi.py
sideload-1.5.0.dist-info/WHEEL
sideload-1.5.0.dist-info/entry_points.txt
sideload-1.5.0.dist-info/METADATA
sideload-1.5.0.dist-info/RECORD
