Metadata-Version: 2.3
Name: sideload
Version: 1.5.0
Summary: Download large files via PyPI packages
Author: Sygmei
Author-email: Sygmei <3835355+Sygmei@users.noreply.github.com>
Requires-Dist: build>=1.3.0
Requires-Dist: twine>=6.2.0
Requires-Dist: wheel>=0.45.1
Requires-Dist: rich>=13.0.0
Requires-Dist: httpx>=0.28.1
Requires-Dist: pip>=25.2
Requires-Dist: playwright>=1.55.0
Requires-Dist: pyotp>=2.9.0
Requires-Python: >=3.12
